{
  "registry": 1,
  "name": "GCU Library",
  "description": "Prepared books and data packs from the Geoscientific Chaos Union.",
  "homepage": "https://github.com/gentropic/gcu-library",
  "updated": "2026-06-02",
  "entries": [
    {
      "name": "arcr",
      "kind": "gcudat",
      "datKind": "books",
      "title": "arcr / gewgaw — The Micro-Game DSL Manual",
      "description": "A tiny, sandboxed DSL for one-screen arcade micro-games small enough to fit in a QR code — written for (and by) language models. The gewgaw reference engine, an example-first cookbook, and the normative spec.",
      "version": "1.0.1",
      "license": "CC0-1.0",
      "attribution": "Geoscientific Chaos Union",
      "size": 26457,
      "url": "dist/arcr.gcudat",
      "integrity": "sha256-j9Oocb9LBMTvzefL2YikEtcIb30icjo5KEGB2DP6K00=",
      "tags": [
        "reference",
        "tutorial",
        "game-dev",
        "dsl"
      ]
    },
    {
      "name": "elements-of-style",
      "kind": "gcudat",
      "datKind": "books",
      "title": "The Elements of Style",
      "description": "The classic concise guide to English usage and composition (1918, original Strunk edition).",
      "version": "1.0.0",
      "license": "Public Domain",
      "attribution": "William Strunk Jr.",
      "size": 35833,
      "url": "dist/elements-of-style.gcudat",
      "integrity": "sha256-qGr+bfJfY9MB01ZHIGf1YDo7yAh2V+uGM3FRdhcQ5f0=",
      "tags": [
        "reference",
        "style",
        "writing",
        "english"
      ]
    },
    {
      "name": "factbook",
      "kind": "gcudat",
      "datKind": "data",
      "title": "CIA World Factbook",
      "description": "Per-country reference data from the CIA World Factbook — population, area, GDP, capital, government, coordinates, and a background blurb for 254 countries and entities.",
      "version": "1.1.0",
      "license": "CC0-1.0",
      "attribution": "US Central Intelligence Agency — public domain",
      "size": 2805117,
      "url": "dist/factbook.gcudat",
      "integrity": "sha256-5RN7IrPsLjlXv/T3m0g73Tc7ublRxpopurTvwH8Velg=",
      "tags": [
        "reference",
        "dataset",
        "geography",
        "countries"
      ]
    },
    {
      "name": "ods",
      "kind": "gcudat",
      "datKind": "books",
      "title": "Open Data Structures (Python edition)",
      "description": "",
      "version": "1.0.0",
      "license": "CC BY 2.5",
      "attribution": "Pat Morin",
      "size": 1916673,
      "url": "dist/ods.gcudat",
      "integrity": "sha256-jphQ3CBgOhy3+VumepDDyb/MeepTl3HAIhah6SJHS/g=",
      "tags": [
        "books"
      ]
    },
    {
      "name": "rtnw",
      "kind": "gcudat",
      "datKind": "books",
      "title": "Ray Tracing: The Next Week",
      "description": "",
      "version": "1.0.1",
      "license": "CC0-1.0",
      "attribution": "Peter Shirley, Trevor David Black, Steve Hollasch",
      "size": 5422875,
      "url": "dist/rtnw.gcudat",
      "integrity": "sha256-Gjpc+tG0ZAkDFLXNGb8rk0fjWvvYm8ZRwuIbePrVDg4=",
      "tags": [
        "books"
      ]
    },
    {
      "name": "rtow",
      "kind": "gcudat",
      "datKind": "books",
      "title": "Ray Tracing in One Weekend",
      "description": "",
      "version": "1.0.1",
      "license": "CC0-1.0",
      "attribution": "Peter Shirley, Trevor David Black, Steve Hollasch",
      "size": 2524984,
      "url": "dist/rtow.gcudat",
      "integrity": "sha256-UzNenrf/0po9UYpNuzh3pMb2BAIsb/JqO56M9f3HpHM=",
      "tags": [
        "books"
      ]
    },
    {
      "name": "rtrol",
      "kind": "gcudat",
      "datKind": "books",
      "title": "Ray Tracing: The Rest of Your Life",
      "description": "",
      "version": "1.0.1",
      "license": "CC0-1.0",
      "attribution": "Peter Shirley, Trevor David Black, Steve Hollasch",
      "size": 3534526,
      "url": "dist/rtrol.gcudat",
      "integrity": "sha256-exWYU2bTfR5Saad1YjaskkcPe47CWxuv+y1ZaiS3XNM=",
      "tags": [
        "books"
      ]
    }
  ]
}
